{
	"archive" : {},
	"artifacts" : 
	[
		{
			"path" : "src/libRenderCore.a"
		}
	],
	"backtrace" : 1,
	"backtraceGraph" : 
	{
		"commands" : 
		[
			"add_library",
			"target_link_libraries",
			"target_include_directories"
		],
		"files" : 
		[
			"src/CMakeLists.txt"
		],
		"nodes" : 
		[
			{
				"file" : 0
			},
			{
				"command" : 0,
				"file" : 0,
				"line" : 2,
				"parent" : 0
			},
			{
				"command" : 1,
				"file" : 0,
				"line" : 6,
				"parent" : 0
			},
			{
				"command" : 2,
				"file" : 0,
				"line" : 4,
				"parent" : 0
			}
		]
	},
	"codemodelVersion" : 
	{
		"major" : 2,
		"minor" : 10
	},
	"compileDependencies" : 
	[
		{
			"backtrace" : 2,
			"id" : "Vulkan::Vulkan::@6890427a1f51a3e7e1df"
		},
		{
			"backtrace" : 2,
			"id" : "glfw::@6890427a1f51a3e7e1df"
		}
	],
	"compileGroups" : 
	[
		{
			"compileCommandFragments" : 
			[
				{
					"fragment" : "-g -std=gnu++20"
				}
			],
			"includes" : 
			[
				{
					"backtrace" : 3,
					"path" : "/mnt/hdd/c++/Vulkan/RenderCore/include"
				}
			],
			"language" : "CXX",
			"languageStandard" : 
			{
				"backtraces" : 
				[
					1
				],
				"standard" : "20"
			},
			"sourceIndexes" : 
			[
				0,
				1,
				2,
				3,
				4,
				5,
				6,
				7,
				8,
				9,
				10,
				11,
				12,
				13,
				14
			]
		}
	],
	"id" : "RenderCore::@145eef247bfb46b6828c",
	"interfaceCompileDependencies" : 
	[
		{
			"backtrace" : 2,
			"id" : "Vulkan::Vulkan::@6890427a1f51a3e7e1df"
		},
		{
			"backtrace" : 2,
			"id" : "glfw::@6890427a1f51a3e7e1df"
		}
	],
	"interfaceLinkLibraries" : 
	[
		{
			"backtrace" : 2,
			"id" : "Vulkan::Vulkan::@6890427a1f51a3e7e1df"
		},
		{
			"backtrace" : 2,
			"id" : "glfw::@6890427a1f51a3e7e1df"
		}
	],
	"linkLibraries" : 
	[
		{
			"backtrace" : 2,
			"id" : "Vulkan::Vulkan::@6890427a1f51a3e7e1df"
		},
		{
			"backtrace" : 2,
			"id" : "glfw::@6890427a1f51a3e7e1df"
		}
	],
	"name" : "RenderCore",
	"nameOnDisk" : "libRenderCore.a",
	"paths" : 
	{
		"build" : "src",
		"source" : "src"
	},
	"sourceGroups" : 
	[
		{
			"name" : "Source Files",
			"sourceIndexes" : 
			[
				0,
				1,
				2,
				3,
				4,
				5,
				6,
				7,
				8,
				9,
				10,
				11,
				12,
				13,
				14
			]
		}
	],
	"sources" : 
	[
		{
			"backtrace" : 1,
			"compileGroupIndex" : 0,
			"path" : "src/RenderCore.cpp",
			"sourceGroupIndex" : 0
		},
		{
			"backtrace" : 1,
			"compileGroupIndex" : 0,
			"path" : "src/engine/shader.cpp",
			"sourceGroupIndex" : 0
		},
		{
			"backtrace" : 1,
			"compileGroupIndex" : 0,
			"path" : "src/engine/texture.cpp",
			"sourceGroupIndex" : 0
		},
		{
			"backtrace" : 1,
			"compileGroupIndex" : 0,
			"path" : "src/engine/vertex.cpp",
			"sourceGroupIndex" : 0
		},
		{
			"backtrace" : 1,
			"compileGroupIndex" : 0,
			"path" : "src/engine/window.cpp",
			"sourceGroupIndex" : 0
		},
		{
			"backtrace" : 1,
			"compileGroupIndex" : 0,
			"path" : "src/vulkanBackend/framebufferManager.cpp",
			"sourceGroupIndex" : 0
		},
		{
			"backtrace" : 1,
			"compileGroupIndex" : 0,
			"path" : "src/vulkanBackend/render/vulkanCommandBuffer.cpp",
			"sourceGroupIndex" : 0
		},
		{
			"backtrace" : 1,
			"compileGroupIndex" : 0,
			"path" : "src/vulkanBackend/render/vulkanPipeline.cpp",
			"sourceGroupIndex" : 0
		},
		{
			"backtrace" : 1,
			"compileGroupIndex" : 0,
			"path" : "src/vulkanBackend/render/vulkanRenderPass.cpp",
			"sourceGroupIndex" : 0
		},
		{
			"backtrace" : 1,
			"compileGroupIndex" : 0,
			"path" : "src/vulkanBackend/render/vulkanRenderer.cpp",
			"sourceGroupIndex" : 0
		},
		{
			"backtrace" : 1,
			"compileGroupIndex" : 0,
			"path" : "src/vulkanBackend/utils.cpp",
			"sourceGroupIndex" : 0
		},
		{
			"backtrace" : 1,
			"compileGroupIndex" : 0,
			"path" : "src/vulkanBackend/vulkanBuffer.cpp",
			"sourceGroupIndex" : 0
		},
		{
			"backtrace" : 1,
			"compileGroupIndex" : 0,
			"path" : "src/vulkanBackend/vulkanContext.cpp",
			"sourceGroupIndex" : 0
		},
		{
			"backtrace" : 1,
			"compileGroupIndex" : 0,
			"path" : "src/vulkanBackend/vulkanDevice.cpp",
			"sourceGroupIndex" : 0
		},
		{
			"backtrace" : 1,
			"compileGroupIndex" : 0,
			"path" : "src/vulkanBackend/vulkanSwapchain.cpp",
			"sourceGroupIndex" : 0
		}
	],
	"type" : "STATIC_LIBRARY"
}
